lexrpc/__init__.py
lexrpc/base.py
lexrpc/client.py
lexrpc/flask_server.py
lexrpc/server.py
lexrpc/lexicons/app/bsky/actor/defs.json
lexrpc/lexicons/app/bsky/actor/getPreferences.json
lexrpc/lexicons/app/bsky/actor/getProfile.json
lexrpc/lexicons/app/bsky/actor/getProfiles.json
lexrpc/lexicons/app/bsky/actor/getSuggestions.json
lexrpc/lexicons/app/bsky/actor/profile.json
lexrpc/lexicons/app/bsky/actor/putPreferences.json
lexrpc/lexicons/app/bsky/actor/searchActors.json
lexrpc/lexicons/app/bsky/actor/searchActorsTypeahead.json
lexrpc/lexicons/app/bsky/actor/status.json
lexrpc/lexicons/app/bsky/bookmark/createBookmark.json
lexrpc/lexicons/app/bsky/bookmark/defs.json
lexrpc/lexicons/app/bsky/bookmark/deleteBookmark.json
lexrpc/lexicons/app/bsky/bookmark/getBookmarks.json
lexrpc/lexicons/app/bsky/embed/defs.json
lexrpc/lexicons/app/bsky/embed/external.json
lexrpc/lexicons/app/bsky/embed/images.json
lexrpc/lexicons/app/bsky/embed/record.json
lexrpc/lexicons/app/bsky/embed/recordWithMedia.json
lexrpc/lexicons/app/bsky/embed/video.json
lexrpc/lexicons/app/bsky/feed/defs.json
lexrpc/lexicons/app/bsky/feed/describeFeedGenerator.json
lexrpc/lexicons/app/bsky/feed/generator.json
lexrpc/lexicons/app/bsky/feed/getActorFeeds.json
lexrpc/lexicons/app/bsky/feed/getActorLikes.json
lexrpc/lexicons/app/bsky/feed/getAuthorFeed.json
lexrpc/lexicons/app/bsky/feed/getFeed.json
lexrpc/lexicons/app/bsky/feed/getFeedGenerator.json
lexrpc/lexicons/app/bsky/feed/getFeedGenerators.json
lexrpc/lexicons/app/bsky/feed/getFeedSkeleton.json
lexrpc/lexicons/app/bsky/feed/getLikes.json
lexrpc/lexicons/app/bsky/feed/getListFeed.json
lexrpc/lexicons/app/bsky/feed/getPostThread.json
lexrpc/lexicons/app/bsky/feed/getPosts.json
lexrpc/lexicons/app/bsky/feed/getQuotes.json
lexrpc/lexicons/app/bsky/feed/getRepostedBy.json
lexrpc/lexicons/app/bsky/feed/getSuggestedFeeds.json
lexrpc/lexicons/app/bsky/feed/getTimeline.json
lexrpc/lexicons/app/bsky/feed/like.json
lexrpc/lexicons/app/bsky/feed/post.json
lexrpc-2.0.dist-info/licenses/LICENSE
lexrpc-2.0.dist-info/METADATA
lexrpc-2.0.dist-info/WHEEL
lexrpc-2.0.dist-info/top_level.txt
lexrpc-2.0.dist-info/RECORD
