Metadata-Version: 2.4
Name: lexrpc
Version: 2.0
Summary: Python implementation of AT Protocol's XRPC + Lexicon
Author-email: Ryan Barrett <lexrpc@ryanb.org>
Project-URL: Homepage, https://github.com/snarfed/lexrpc
Project-URL: Documentation, https://lexrpc.readthedocs.io/
Keywords: XRPC,Lexicon,AT Protocol,ATP
Classifier: Programming Language :: Python :: 3
Classifier: License :: Public Domain
Classifier: Operating System :: OS Independent
Classifier: Intended Audience :: Developers
Classifier: Development Status :: 3 - Alpha
Classifier: Topic :: Software Development :: Libraries :: Python Modules
Requires-Python: >=3.7
License-File: LICENSE
Requires-Dist: dag-cbor
Requires-Dist: dag-json>=0.3
Requires-Dist: grapheme
Requires-Dist: iterators
Requires-Dist: libipld<4.0.0
Requires-Dist: multiformats>=0.3.1.post4
Requires-Dist: requests>=2.0
Requires-Dist: simple-websocket
Provides-Extra: flask
Requires-Dist: Flask>=2.0; extra == "flask"
Requires-Dist: flask-sock; extra == "flask"
Dynamic: license-file
